{
  "identificador": "Real Decreto 2822/1998, de 23 de diciembre.",
  "fecha_actualizacion": "N/A",
  "tematica": "Reglamento General de Vehículos.",
  "modelo_sancion": "modelo_estandar",
  "rango": "Real Decreto Ley",
  "ambito": "Estatal",
  "areaId": "trafico",
  "infracciones": [
    {
      "tipo": "grave",
      "circulo": "MG",
      "norma": "Reglamento General de Vehículos",
      "articulo": "1",
      "apartado": "1",
      "opc": "5B",
      "puntos": "0",
      "importe": "500 €",
      "importe_reducido": "250 €",
      "descripcion": "Circular con un vehículo que **carece de la correspondiente autorización administrativa**.",
      "tags": [
        "carencia aut. para circular",
        "autorizacion administrativa"
      ],
      "nota": "Aplicable a vehículos no susceptibles de matriculación sin homologación previa (ej. minimotos). Posible inmovilización",
      "responsables": [
        "Titular",
        "Conductor"
      ]
    },
    {
      "tipo": "grave",
      "circulo": "MG",
      "norma": "Reglamento General de Vehículos",
      "articulo": "1",
      "apartado": "2",
      "opc": "5A",
      "puntos": "0",
      "importe": "500 €",
      "importe_reducido": "250 €",
      "descripcion": "Circular con el vehículo reseñado **sin haber obtenido, previamente, la autorización administrativa** correspondiente.",
      "tags": [
        "carencia aut. para circular",
        "matriculacion",
        "autorizacion administrativa"
      ],
      "nota": "Aplicable a vehículos susceptibles de matriculación (ej. sin alta tras baja temporal, matrícula extranjera sin matricular en España). Posible inmovilización",
      "responsables": [
        "Titular",
        "Conductor"
      ]
    },
    {
      "tipo": "grave",
      "circulo": "MG",
      "norma": "Reglamento General de Vehículos",
      "articulo": "1",
      "apartado": "2",
      "opc": "5B",
      "puntos": "0",
      "importe": "500 €",
      "importe_reducido": "250 €",
      "descripcion": "Circular con un vehículo cuya autorización administrativa ha sido objeto de **anulación o declarada su pérdida de vigencia**.",
      "tags": [
        "carencia aut. para circular",
        "anulacion",
        "perdida de vigencia"
      ],
      "nota": "Posible inmovilización",
      "responsables": [
        "Titular",
        "Conductor"
      ]
    },
    {
      "tipo": "media",
      "circulo": "G",
      "norma": "Reglamento General de Vehículos",
      "articulo": "1",
      "apartado": "2",
      "opc": "5C",
      "puntos": "0",
      "importe": "200 €",
      "importe_reducido": "100 €",
      "descripcion": "Circular con el vehículo reseñado estando **suspendido el permiso de circulación** del mismo.",
      "tags": [
        "carencia aut. para circular",
        "permiso suspendido"
      ],
      "nota": "Posible inmovilización",
      "responsables": [
        "Titular",
        "Conductor"
      ]
    },
    {
      "tipo": "media",
      "circulo": "G",
      "norma": "Reglamento General de Vehículos",
      "articulo": "1",
      "apartado": "2",
      "opc": "5D",
      "puntos": "0",
      "importe": "200 €",
      "importe_reducido": "100 €",
      "descripcion": "Poner en circulación el vehículo reseñado careciendo de la correspondiente autorización administrativa, figurando en situación de **baja en el registro de vehículos**.",
      "tags": [
        "carencia aut. para circular",
        "dado de baja"
      ],
      "nota": "Supuesto para vehículos estacionados cuya apariencia no permite deducir su abandono",
      "responsables": [
        "Titular",
        "Conductor"
      ]
    },
    {
      "tipo": "grave",
      "circulo": "MG",
      "norma": "Reglamento General de Vehículos",
      "articulo": "6",
      "apartado": "-",
      "opc": "5A",
      "puntos": "0",
      "importe": "3000 €",
      "importe_reducido": "SIN REDUC.",
      "descripcion": "Puesta en servicio o venta de **componentes y unidades técnicas independientes incumpliendo la reglamentación** legalmente establecida para su montaje en vehículos.",
      "tags": [
        "condiciones tecnicas",
        "componentes",
        "homologacion"
      ],
      "nota": "",
      "responsables": []
    },
    {
      "tipo": "media",
      "circulo": "G",
      "norma": "Reglamento General de Vehículos",
      "articulo": "7",
      "apartado": "2",
      "opc": "5B",
      "puntos": "0",
      "importe": "200 €",
      "importe_reducido": "100 €",
      "descripcion": "Efectuar una **reforma de importancia** en el vehículo reseñado **sin haberla regularizado** ante el órgano competente en materia de industria.",
      "tags": [
        "reformas de importancia",
        "itv",
        "homologacion"
      ],
      "nota": "Especificar la reforma realizada",
      "responsables": [
        "Titular"
      ]
    },
    {
      "tipo": "grave",
      "circulo": "MG",
      "norma": "Reglamento General de Vehículos",
      "articulo": "7",
      "apartado": "2",
      "opc": "5C",
      "puntos": "0",
      "importe": "500 €",
      "importe_reducido": "250 €",
      "descripcion": "Efectuar una **reforma de importancia** en el vehículo reseñado sin haberla regularizado, **afectando gravemente a la seguridad vial**.",
      "tags": [
        "reformas de importancia",
        "itv",
        "seguridad vial"
      ],
      "nota": "Posible inmovilización. Especificar la reforma y por qué afecta a la seguridad",
      "responsables": [
        "Titular"
      ]
    },
    {
      "tipo": "grave",
      "circulo": "MG",
      "norma": "Reglamento General de Vehículos",
      "articulo": "7",
      "apartado": "3",
      "opc": "5A",
      "puntos": "0",
      "importe": "500 €",
      "importe_reducido": "250 €",
      "descripcion": "Proceder a la **sustitución, añadido o supresión de piezas** o elementos sujetos a una reglamentación técnica por otros que no la cumplan, **afectando gravemente a la seguridad vial**.",
      "tags": [
        "condiciones tecnicas",
        "seguridad vial",
        "piezas no homologadas"
      ],
      "nota": "Por ejemplo: bastidor, dirección, suspensión, neumáticos, frenos, etc. Posible inmovilización",
      "responsables": [
        "Titular"
      ]
    },
    {
      "tipo": "media",
      "circulo": "G",
      "norma": "Reglamento General de Vehículos",
      "articulo": "7",
      "apartado": "3",
      "opc": "5B",
      "puntos": "0",
      "importe": "200 €",
      "importe_reducido": "100 €",
      "descripcion": "Proceder a la **sustitución, añadido o supresión de piezas** o elementos sujetos a una reglamentación técnica por otros que no la cumplan o no correspondan al vehículo.",
      "tags": [
        "condiciones tecnicas",
        "piezas no homologadas"
      ],
      "nota": "Para alteraciones que no afecten gravemente a la seguridad vial",
      "responsables": [
        "Titular"
      ]
    },
    {
      "tipo": "media",
      "circulo": "G",
      "norma": "Reglamento General de Vehículos",
      "articulo": "8",
      "apartado": "1",
      "opc": "5A",
      "puntos": "0",
      "importe": "200 €",
      "importe_reducido": "100 €",
      "descripcion": "Circular con un vehículo que no lleve las **placas o inscripciones reglamentarias**.",
      "tags": [
        "placas",
        "inscripciones",
        "condiciones tecnicas"
      ],
      "nota": "Este supuesto no se refiere a las placas de matrícula",
      "responsables": [
        "Titular"
      ]
    },
    {
      "tipo": "media",
      "circulo": "G",
      "norma": "Reglamento General de Vehículos",
      "articulo": "8",
      "apartado": "1",
      "opc": "5B",
      "puntos": "0",
      "importe": "200 €",
      "importe_reducido": "100 €",
      "descripcion": "Efectuar **cambios o retoques en los números de identificación del bastidor** del vehículo, así como en las placas e inscripciones reglamentarias.",
      "tags": [
        "placas",
        "bastidor",
        "manipulacion"
      ],
      "nota": "Podría ser constitutivo de delito de falsedad",
      "responsables": [
        "Titular"
      ]
    },
    {
      "tipo": "grave",
      "circulo": "MG",
      "norma": "Reglamento General de Vehículos",
      "articulo": "8",
      "apartado": "2",
      "opc": "5B",
      "puntos": "0",
      "importe": "500 €",
      "importe_reducido": "250 €",
      "descripcion": "**Sustituir total o parcialmente el bastidor** o estructura autoportante afectando al número de identificación del vehículo, en forma contraria a lo establecido y **afectando gravemente a la seguridad vial**.",
      "tags": [
        "condiciones tecnicas",
        "bastidor",
        "seguridad vial"
      ],
      "nota": "Posible inmovilización",
      "responsables": [
        "Titular"
      ]
    },
    {
      "tipo": "media",
      "circulo": "G",
      "norma": "Reglamento General de Vehículos",
      "articulo": "8",
      "apartado": "2",
      "opc": "5C",
      "puntos": "0",
      "importe": "200 €",
      "importe_reducido": "100 €",
      "descripcion": "**Sustituir total o parcialmente el bastidor** o estructura autoportante afectando al número de identificación del vehículo, en forma contraria a lo establecido reglamentariamente.",
      "tags": [
        "condiciones tecnicas",
        "bastidor"
      ],
      "nota": "",
      "responsables": [
        "Titular"
      ]
    },
    {
      "tipo": "grave",
      "circulo": "MG",
      "norma": "Reglamento General de Vehículos",
      "articulo": "9",
      "apartado": "1",
      "opc": "5B",
      "puntos": "0",
      "importe": "500 €",
      "importe_reducido": "250 €",
      "descripcion": "Circular con un conjunto de vehículos **incumpliendo las reglas de compatibilidad** establecidas reglamentariamente, **afectando gravemente a la seguridad vial**.",
      "tags": [
        "remolque de vehiculos",
        "compatibilidad",
        "seguridad vial"
      ],
      "nota": "Posible inmovilización",
      "responsables": [
        "Titular",
        "Conductor"
      ]
    },
    {
      "tipo": "media",
      "circulo": "G",
      "norma": "Reglamento General de Vehículos",
      "articulo": "9",
      "apartado": "1",
      "opc": "5C",
      "puntos": "0",
      "importe": "200 €",
      "importe_reducido": "100 €",
      "descripcion": "Circular con un conjunto de vehículos **incumpliendo las reglas de compatibilidad** establecidas reglamentariamente.",
      "tags": [
        "remolque de vehiculos",
        "compatibilidad"
      ],
      "nota": "",
      "responsables": [
        "Titular",
        "Conductor"
      ]
    },
    {
      "tipo": "media",
      "circulo": "G",
      "norma": "Reglamento General de Vehículos",
      "articulo": "9",
      "apartado": "2",
      "opc": "5B",
      "puntos": "0",
      "importe": "200 €",
      "importe_reducido": "100 €",
      "descripcion": "Circular con el vehículo reseñado **arrastrando más de un remolque** o semirremolque, en forma antirreglamentaria.",
      "tags": [
        "remolque de vehiculos",
        "doble remolque"
      ],
      "nota": "",
      "responsables": [
        "Titular",
        "Conductor"
      ]
    },
    {
      "tipo": "grave",
      "circulo": "MG",
      "norma": "Reglamento General de Vehículos",
      "articulo": "9",
      "apartado": "3",
      "opc": "5C",
      "puntos": "0",
      "importe": "500 €",
      "importe_reducido": "250 €",
      "descripcion": "Circular con el vehículo reseñado arrastrando una caravana o remolque ligero que **no está dotado de Tarjeta de Inspección Técnica**.",
      "tags": [
        "carencia aut. para circular",
        "remolque",
        "caravana",
        "itv"
      ],
      "nota": "Aplicable a remolques con MMA de hasta 750 kg",
      "responsables": [
        "Titular"
      ]
    },
    {
      "tipo": "media",
      "circulo": "G",
      "norma": "Reglamento General de Vehículos",
      "articulo": "10",
      "apartado": "1",
      "opc": "5A",
      "puntos": "0",
      "importe": "200 €",
      "importe_reducido": "100 €",
      "descripcion": "No haberse sometido el vehículo reseñado a la **inspección técnica periódica (ITV)** establecida reglamentariamente.",
      "tags": [
        "i.t.v.",
        "itv caducada"
      ],
      "nota": "",
      "responsables": [
        "Titular",
        "Arrendatario"
      ]
    },
    {
      "tipo": "grave",
      "circulo": "MG",
      "norma": "Reglamento General de Vehículos",
      "articulo": "10",
      "apartado": "1",
      "opc": "5B",
      "puntos": "0",
      "importe": "500 €",
      "importe_reducido": "250 €",
      "descripcion": "Circular con el vehículo reseñado cuya **inspección técnica ha resultado negativa** por incumplir las condiciones técnicas que garantizan la seguridad vial.",
      "tags": [
        "i.t.v.",
        "itv negativa",
        "seguridad vial"
      ],
      "nota": "El vehículo no puede circular en ningún caso. Posible inmovilización",
      "responsables": [
        "Titular",
        "Arrendatario"
      ]
    },
    {
      "tipo": "media",
      "circulo": "G",
      "norma": "Reglamento General de Vehículos",
      "articulo": "10",
      "apartado": "1",
      "opc": "5C",
      "puntos": "0",
      "importe": "200 €",
      "importe_reducido": "100 €",
      "descripcion": "Circular con el vehículo reseñado cuya **inspección técnica ha resultado desfavorable**.",
      "tags": [
        "i.t.v.",
        "itv desfavorable"
      ],
      "nota": "Sólo podrá circular para su traslado al taller o para volver a la estación de ITV",
      "responsables": [
        "Titular",
        "Arrendatario"
      ]
    },
    {
      "tipo": "grave",
      "circulo": "MG",
      "norma": "Reglamento General de Vehículos",
      "articulo": "10",
      "apartado": "1",
      "opc": "5D",
      "puntos": "0",
      "importe": "500 €",
      "importe_reducido": "250 €",
      "descripcion": "Circular el vehículo reseñado, habiendo quedado inhabilitado para ello al **no haber sido sometido a una nueva inspección en el plazo máximo** establecido, tras un primer resultado desfavorable.",
      "tags": [
        "i.t.v.",
        "itv desfavorable",
        "plazo vencido"
      ],
      "nota": "",
      "responsables": [
        "Titular",
        "Arrendatario"
      ]
    },
    {
      "tipo": "media",
      "circulo": "G",
      "norma": "Reglamento General de Vehículos",
      "articulo": "10",
      "apartado": "1",
      "opc": "5E",
      "puntos": "0",
      "importe": "200 €",
      "importe_reducido": "100 €",
      "descripcion": "Poner en circulación el vehículo reseñado (estacionado), cuya última inspección técnica ha resultado **desfavorable**, habiéndose superado el plazo máximo para ser sometido a nueva inspección.",
      "tags": [
        "i.t.v.",
        "itv desfavorable",
        "estacionado"
      ],
      "nota": "Aplicable a vehículos en la vía pública sin estar circulando",
      "responsables": [
        "Titular",
        "Arrendatario"
      ]
    },
    {
      "tipo": "media",
      "circulo": "G",
      "norma": "Reglamento General de Vehículos",
      "articulo": "10",
      "apartado": "1",
      "opc": "5F",
      "puntos": "0",
      "importe": "200 €",
      "importe_reducido": "100 €",
      "descripcion": "Poner en circulación el vehículo reseñado (estacionado), cuya última inspección técnica ha resultado **negativa**, habiendo quedado inhabilitado para circular.",
      "tags": [
        "i.t.v.",
        "itv negativa",
        "estacionado"
      ],
      "nota": "Aplicable a vehículos en la vía pública sin estar circulando",
      "responsables": [
        "Titular",
        "Arrendatario"
      ]
    },
    {
      "tipo": "media",
      "circulo": "G",
      "norma": "Reglamento General de Vehículos",
      "articulo": "11",
      "apartado": "-",
      "opc": "5E",
      "puntos": "0",
      "importe": "200 €",
      "importe_reducido": "100 €",
      "descripcion": "Circular con el vehículo reseñado sin estar provisto de **parabrisas y dispositivos lavaparabrisas** en las dimensiones y formas establecidas.",
      "tags": [
        "condiciones tecnicas",
        "parabrisas",
        "lavaparabrisas"
      ],
      "nota": "",
      "responsables": [
        "Titular"
      ]
    },
    {
      "tipo": "media",
      "circulo": "G",
      "norma": "Reglamento General de Vehículos",
      "articulo": "11",
      "apartado": "-",
      "opc": "5F",
      "puntos": "0",
      "importe": "200 €",
      "importe_reducido": "100 €",
      "descripcion": "Circular con un vehículo cuyos **elementos transparentes incumplen lo establecido** reglamentariamente en lo que respecta a su afectación al campo de visión del conductor.",
      "tags": [
        "condiciones tecnicas",
        "visibilidad",
        "cristales"
      ],
      "nota": "",
      "responsables": [
        "Titular"
      ]
    },
    {
      "tipo": "grave",
      "circulo": "MG",
      "norma": "Reglamento General de Vehículos",
      "articulo": "11",
      "apartado": "-",
      "opc": "5G",
      "puntos": "0",
      "importe": "500 €",
      "importe_reducido": "250 €",
      "descripcion": "Circular con el vehículo reseñado cuyos **órganos de dirección no se ajustan a las prescripciones técnicas** fijadas reglamentariamente.",
      "tags": [
        "condiciones tecnicas",
        "seguridad vial",
        "direccion"
      ],
      "nota": "Si afecta manifiestamente a la seguridad, podría ser conducción temeraria",
      "responsables": [
        "Titular"
      ]
    },
    {
      "tipo": "media",
      "circulo": "G",
      "norma": "Reglamento General de Vehículos",
      "articulo": "11",
      "apartado": "-",
      "opc": "5H",
      "puntos": "0",
      "importe": "200 €",
      "importe_reducido": "100 €",
      "descripcion": "Circular con un vehículo desprovisto de dispositivo que permita la **marcha atrás**.",
      "tags": [
        "condiciones tecnicas",
        "marcha atras"
      ],
      "nota": "Excepto motocicletas y algunos vehículos de tres ruedas",
      "responsables": [
        "Titular"
      ]
    },
    {
      "tipo": "media",
      "circulo": "G",
      "norma": "Reglamento General de Vehículos",
      "articulo": "11",
      "apartado": "-",
      "opc": "5I",
      "puntos": "0",
      "importe": "200 €",
      "importe_reducido": "100 €",
      "descripcion": "Circular con un vehículo desprovisto de un aparato productor de **señales acústicas** en la forma establecida reglamentariamente.",
      "tags": [
        "condiciones tecnicas",
        "claxon",
        "bocina"
      ],
      "nota": "",
      "responsables": [
        "Titular"
      ]
    },
    {
      "tipo": "media",
      "circulo": "G",
      "norma": "Reglamento General de Vehículos",
      "articulo": "11",
      "apartado": "-",
      "opc": "5J",
      "puntos": "0",
      "importe": "200 €",
      "importe_reducido": "100 €",
      "descripcion": "Circular con un vehículo no prioritario con **aparatos emisores de señales acústicas especiales**.",
      "tags": [
        "condiciones tecnicas",
        "sirena",
        "uso indebido"
      ],
      "nota": "",
      "responsables": [
        "Titular"
      ]
    },
    {
      "tipo": "media",
      "circulo": "G",
      "norma": "Reglamento General de Vehículos",
      "articulo": "11",
      "apartado": "-",
      "opc": "5K",
      "puntos": "0",
      "importe": "200 €",
      "importe_reducido": "100 €",
      "descripcion": "Circular con un vehículo cuyos **órganos de maniobra e indicadores no puedan ser fácilmente identificados y accionados** de forma instantánea por el conductor.",
      "tags": [
        "condiciones tecnicas",
        "mandos",
        "indicadores"
      ],
      "nota": "",
      "responsables": [
        "Titular"
      ]
    },
    {
      "tipo": "media",
      "circulo": "G",
      "norma": "Reglamento General de Vehículos",
      "articulo": "11",
      "apartado": "-",
      "opc": "5L",
      "puntos": "0",
      "importe": "200 €",
      "importe_reducido": "100 €",
      "descripcion": "Circular con un vehículo cuyos **órganos mecánicos o equipos complementarios supongan peligro** para los usuarios de la vía pública.",
      "tags": [
        "condiciones tecnicas",
        "peligro",
        "mecanica"
      ],
      "nota": "Deberá especificarse el supuesto concreto que constituye peligro",
      "responsables": []
    },
    {
      "tipo": "media",
      "circulo": "G",
      "norma": "Reglamento General de Vehículos",
      "articulo": "11",
      "apartado": "-",
      "opc": "5M",
      "puntos": "0",
      "importe": "200 €",
      "importe_reducido": "100 €",
      "descripcion": "Circular con el vehículo reseñado cuyos **órganos motores no se ajustan a las prescripciones técnicas** fijadas reglamentariamente.",
      "tags": [
        "condiciones tecnicas",
        "motor"
      ],
      "nota": "",
      "responsables": [
        "Titular"
      ]
    },
    {
      "tipo": "grave",
      "circulo": "MG",
      "norma": "Reglamento General de Vehículos",
      "articulo": "11",
      "apartado": "-",
      "opc": "5N",
      "puntos": "0",
      "importe": "500 €",
      "importe_reducido": "250 €",
      "descripcion": "Circular con el vehículo provisto de depósitos, tubos y piezas que contengan **materia inflamable que no cumplan las prescripciones técnicas**.",
      "tags": [
        "condiciones tecnicas",
        "seguridad vial",
        "materia inflamable",
        "incendio"
      ],
      "nota": "Aplicable cuando los órganos motores constituyan causa de peligro, riesgo de incendio o explosión",
      "responsables": [
        "Titular"
      ]
    },
    {
      "tipo": "media",
      "circulo": "G",
      "norma": "Reglamento General de Vehículos",
      "articulo": "11",
      "apartado": "-",
      "opc": "5O",
      "puntos": "0",
      "importe": "200 €",
      "importe_reducido": "100 €",
      "descripcion": "Circular con un vehículo de motor capaz de alcanzar en llano una velocidad superior a los 40 km/h **desprovisto de indicador de velocidad**.",
      "tags": [
        "condiciones tecnicas",
        "velocimetro"
      ],
      "nota": "",
      "responsables": [
        "Titular"
      ]
    },
    {
      "tipo": "media",
      "circulo": "G",
      "norma": "Reglamento General de Vehículos",
      "articulo": "11",
      "apartado": "-",
      "opc": "5P",
      "puntos": "0",
      "importe": "200 €",
      "importe_reducido": "100 €",
      "descripcion": "Circular con un vehículo de motor **desprovisto de tacógrafo y limitador de velocidad** cuando así se exija reglamentariamente.",
      "tags": [
        "condiciones tecnicas",
        "tacografo",
        "limitador de velocidad"
      ],
      "nota": "",
      "responsables": [
        "Titular"
      ]
    },
    {
      "tipo": "grave",
      "circulo": "MG",
      "norma": "Reglamento General de Vehículos",
      "articulo": "11",
      "apartado": "-",
      "opc": "5Q",
      "puntos": "0",
      "importe": "500 €",
      "importe_reducido": "250 €",
      "descripcion": "Circular con un automóvil **sin llevar instalados cinturones de seguridad** u otros sistemas de retención homologados, cuando ello se exija reglamentariamente.",
      "tags": [
        "cinturon - sist. r.",
        "seguridad pasiva",
        "cinturon de seguridad"
      ],
      "nota": "",
      "responsables": [
        "Titular"
      ]
    },
    {
      "tipo": "media",
      "circulo": "G",
      "norma": "Reglamento General de Vehículos",
      "articulo": "11",
      "apartado": "-",
      "opc": "5R",
      "puntos": "0",
      "importe": "200 €",
      "importe_reducido": "100 €",
      "descripcion": "Circular con un vehículo dotado de **apoyacabezas sin que éstos cumplan las prescripciones** establecidas reglamentariamente.",
      "tags": [
        "condiciones tecnicas",
        "apoyacabezas",
        "reposacabezas"
      ],
      "nota": "",
      "responsables": [
        "Titular"
      ]
    },
    {
      "tipo": "media",
      "circulo": "G",
      "norma": "Reglamento General de Vehículos",
      "articulo": "11",
      "apartado": "-",
      "opc": "5S",
      "puntos": "0",
      "importe": "200 €",
      "importe_reducido": "100 €",
      "descripcion": "Circular con un vehículo que no está provisto de un **dispositivo contra su utilización no autorizada** (antirrobo).",
      "tags": [
        "condiciones tecnicas",
        "antirrobo"
      ],
      "nota": "El dispositivo debe permitir poner fuera de servicio o bloquear un órgano esencial del vehículo",
      "responsables": [
        "Titular"
      ]
    },
    {
      "tipo": "media",
      "circulo": "G",
      "norma": "Reglamento General de Vehículos",
      "articulo": "11",
      "apartado": "-",
      "opc": "5T",
      "puntos": "0",
      "importe": "200 €",
      "importe_reducido": "100 €",
      "descripcion": "Circular con el vehículo reseñado careciendo de una **protección eficaz al empotramiento** de vehículos que pudieran chocar por su parte trasera.",
      "tags": [
        "condiciones tecnicas",
        "antiempotramiento"
      ],
      "nota": "Dispositivo antiempotramiento",
      "responsables": [
        "Titular"
      ]
    },
    {
      "tipo": "media",
      "circulo": "G",
      "norma": "Reglamento General de Vehículos",
      "articulo": "11",
      "apartado": "-",
      "opc": "5U",
      "puntos": "0",
      "importe": "200 €",
      "importe_reducido": "100 €",
      "descripcion": "Circular con un vehículo destinado al transporte de mercancías desprovisto de un **dispositivo de protección lateral** cuando así se exija.",
      "tags": [
        "condiciones tecnicas",
        "proteccion lateral",
        "transporte mercancias"
      ],
      "nota": "",
      "responsables": [
        "Titular"
      ]
    },
    {
      "tipo": "media",
      "circulo": "G",
      "norma": "Reglamento General de Vehículos",
      "articulo": "11",
      "apartado": "-",
      "opc": "5V",
      "puntos": "0",
      "importe": "200 €",
      "importe_reducido": "100 €",
      "descripcion": "Circular con un vehículo destinado al transporte de mercancías desprovisto de un **dispositivo antiencastramiento delantero** cuando así se exija.",
      "tags": [
        "condiciones tecnicas",
        "antiencastramiento",
        "transporte mercancias"
      ],
      "nota": "",
      "responsables": [
        "Titular"
      ]
    },
    {
      "tipo": "media",
      "circulo": "G",
      "norma": "Reglamento General de Vehículos",
      "articulo": "11",
      "apartado": "-",
      "opc": "5W",
      "puntos": "0",
      "importe": "200 €",
      "importe_reducido": "100 €",
      "descripcion": "Circular con el vehículo reseñado que no se ajusta a las disposiciones relativas a **ruidos, con el escape libre, sin silenciador o con éste ineficaz**.",
      "tags": [
        "condiciones tecnicas",
        "emisiones",
        "ruido",
        "escape libre"
      ],
      "nota": "",
      "responsables": [
        "Titular"
      ]
    },
    {
      "tipo": "media",
      "circulo": "G",
      "norma": "Reglamento General de Vehículos",
      "articulo": "11",
      "apartado": "-",
      "opc": "5X",
      "puntos": "0",
      "importe": "200 €",
      "importe_reducido": "100 €",
      "descripcion": "Circular con el vehículo reseñado que no se ajusta a las disposiciones relativas a **emisión de humos y gases contaminantes**.",
      "tags": [
        "condiciones tecnicas",
        "emisiones",
        "humos",
        "gases"
      ],
      "nota": "",
      "responsables": [
        "Titular"
      ]
    },
    {
      "tipo": "media",
      "circulo": "G",
      "norma": "Reglamento General de Vehículos",
      "articulo": "11",
      "apartado": "-",
      "opc": "5Y",
      "puntos": "0",
      "importe": "200 €",
      "importe_reducido": "100 €",
      "descripcion": "Circular con un vehículo de motor que no se ajuste a las disposiciones relativas a materia **electromagnéticas**.",
      "tags": [
        "condiciones tecnicas",
        "emisiones",
        "electromagneticas"
      ],
      "nota": "",
      "responsables": [
        "Titular"
      ]
    },
    {
      "tipo": "grave",
      "circulo": "MG",
      "norma": "Reglamento General de Vehículos",
      "articulo": "11",
      "apartado": "-",
      "opc": "5Z",
      "puntos": "0",
      "importe": "500 €",
      "importe_reducido": "250 €",
      "descripcion": "Circular con un vehículo que **incumple las condiciones técnicas... afectando las mismas gravemente a la seguridad vial**.",
      "tags": [
        "condiciones tecnicas",
        "seguridad vial"
      ],
      "nota": "Tipo genérico, se debe especificar la condición que afecta gravemente",
      "responsables": [
        "Titular",
        "Conductor"
      ]
    },
    {
      "tipo": "media",
      "circulo": "G",
      "norma": "Reglamento General de Vehículos",
      "articulo": "11",
      "apartado": "1",
      "opc": "5A",
      "puntos": "0",
      "importe": "200 €",
      "importe_reducido": "100 €",
      "descripcion": "Circular con el vehículo reseñado cuyo **campo de visión no permite una visibilidad diáfana** sobre la vía por la que circula.",
      "tags": [
        "condiciones tecnicas",
        "visibilidad",
        "campo de vision"
      ],
      "nota": "Especificar el elemento transparente que dificulta la visibilidad",
      "responsables": [
        "Titular"
      ]
    },
    {
      "tipo": "media",
      "circulo": "G",
      "norma": "Reglamento General de Vehículos",
      "articulo": "11",
      "apartado": "2",
      "opc": "5A",
      "puntos": "0",
      "importe": "200 €",
      "importe_reducido": "100 €",
      "descripcion": "Circular con un vehículo que **carece del reglamentario número de espejos retrovisores**.",
      "tags": [
        "condiciones tecnicas",
        "espejos retrovisores"
      ],
      "nota": "Indicar el espejo que falta",
      "responsables": [
        "Titular"
      ]
    },
    {
      "tipo": "media",
      "circulo": "G",
      "norma": "Reglamento General de Vehículos",
      "articulo": "12",
      "apartado": "-3",
      "opc": "5A",
      "puntos": "0",
      "importe": "200 €",
      "importe_reducido": "100 €",
      "descripcion": "Circular con el vehículo reseñado cuyas **puertas no tengan cerradura u órgano de fijación** que impida su apertura no deseada.",
      "tags": [
        "condiciones tecnicas",
        "puertas",
        "cerradura"
      ],
      "nota": "",
      "responsables": [
        "Titular"
      ]
    },
    {
      "tipo": "media",
      "circulo": "G",
      "norma": "Reglamento General de Vehículos",
      "articulo": "12",
      "apartado": "-",
      "opc": "5A",
      "puntos": "0",
      "importe": "200 €",
      "importe_reducido": "100 €",
      "descripcion": "Circular con el vehículo reseñado **incumpliendo las condiciones establecidas** reglamentariamente y recogidas en el anexo I.",
      "tags": [
        "condiciones tecnicas"
      ],
      "nota": "Infracción genérica, especificar el incumplimiento",
      "responsables": [
        "Titular",
        "Arrendatario"
      ]
    },
    {
      "tipo": "grave",
      "circulo": "MG",
      "norma": "Reglamento General de Vehículos",
      "articulo": "12",
      "apartado": "-",
      "opc": "5B",
      "puntos": "0",
      "importe": "500 €",
      "importe_reducido": "250 €",
      "descripcion": "Circular con el vehículo reseñado incumpliendo las condiciones establecidas reglamentariamente y recogidas en el anexo I, **afectando gravemente a la seguridad vial**.",
      "tags": [
        "condiciones tecnicas",
        "seguridad vial"
      ],
      "nota": "Posible inmovilización",
      "responsables": [
        "Titular",
        "Arrendatario"
      ]
    },
    {
      "tipo": "media",
      "circulo": "G",
      "norma": "Reglamento General de Vehículos",
      "articulo": "12",
      "apartado": "-",
      "opc": "5C",
      "puntos": "0",
      "importe": "200 €",
      "importe_reducido": "100 €",
      "descripcion": "Circular con el vehículo reseñado teniendo **adornos u objetos con aristas salientes** que presenten peligro para los ocupantes o el resto de los usuarios de la vía.",
      "tags": [
        "condiciones tecnicas",
        "aristas salientes",
        "adornos",
        "peligro"
      ],
      "nota": "",
      "responsables": [
        "Titular"
      ]
    },
    {
      "tipo": "media",
      "circulo": "G",
      "norma": "Reglamento General de Vehículos",
      "articulo": "12",
      "apartado": "-",
      "opc": "5D",
      "puntos": "0",
      "importe": "200 €",
      "importe_reducido": "100 €",
      "descripcion": "Circular con el vehículo reseñado cuyos **asientos no están anclados a la estructura** del vehículo de forma resistente.",
      "tags": [
        "condiciones tecnicas",
        "asientos",
        "anclaje"
      ],
      "nota": "",
      "responsables": [
        "Titular"
      ]
    },
    {
      "tipo": "media",
      "circulo": "G",
      "norma": "Reglamento General de Vehículos",
      "articulo": "12",
      "apartado": "4-1",
      "opc": "5A",
      "puntos": "0",
      "importe": "200 €",
      "importe_reducido": "100 €",
      "descripcion": "Circular con el vehículo reseñado cuyos **materiales transparentes no ofrecen una calidad, resistencia y elasticidad suficientes** para reducir al máximo los riesgos de lesiones en caso de impacto.",
      "tags": [
        "condiciones tecnicas",
        "cristales",
        "seguridad"
      ],
      "nota": "",
      "responsables": [
        "Titular"
      ]
    },
    {
      "tipo": "media",
      "circulo": "G",
      "norma": "Reglamento General de Vehículos",
      "articulo": "12",
      "apartado": "4-2",
      "opc": "5B",
      "puntos": "0",
      "importe": "200 €",
      "importe_reducido": "100 €",
      "descripcion": "Circular con un vehículo autorizado a transportar simultáneamente personas y carga, **sin una protección adecuada a la carga** que transporta.",
      "tags": [
        "condiciones tecnicas",
        "proteccion carga",
        "carga"
      ],
      "nota": "",
      "responsables": [
        "Titular",
        "Conductor"
      ]
    },
    {
      "tipo": "media",
      "circulo": "G",
      "norma": "Reglamento General de Vehículos",
      "articulo": "12",
      "apartado": "5-1",
      "opc": "5A",
      "puntos": "0",
      "importe": "200 €",
      "importe_reducido": "100 €",
      "descripcion": "Circular con el vehículo reseñado cuyos neumáticos **no presentan dibujo en las ranuras principales** de la banda de rodamiento.",
      "tags": [
        "neumaticos",
        "desgaste",
        "dibujo neumatico"
      ],
      "nota": "Se formulará una denuncia por cada neumático en mal estado",
      "responsables": [
        "Titular"
      ]
    },
    {
      "tipo": "media",
      "circulo": "G",
      "norma": "Reglamento General de Vehículos",
      "articulo": "12",
      "apartado": "5-1",
      "opc": "5C",
      "puntos": "0",
      "importe": "200 €",
      "importe_reducido": "100 €",
      "descripcion": "Circular con un vehículo cuyos neumáticos **no reúnan las condiciones mínimas de utilización**.",
      "tags": [
        "neumaticos",
        "mal estado",
        "condiciones minimas"
      ],
      "nota": "Ampollas, deformaciones, roturas, cables al descubierto, etc",
      "responsables": [
        "Titular"
      ]
    },
    {
      "tipo": "media",
      "circulo": "G",
      "norma": "Reglamento General de Vehículos",
      "articulo": "12",
      "apartado": "5-1",
      "opc": "5D",
      "puntos": "0",
      "importe": "200 €",
      "importe_reducido": "100 €",
      "descripcion": "Circular con un vehículo cuyo sistema de rodadura tenga **superficies metálicas, estriadas o con salientes**, sin estar equipado con protecciones adecuadas.",
      "tags": [
        "condiciones tecnicas",
        "ruedas",
        "protecciones"
      ],
      "nota": "",
      "responsables": [
        "Titular"
      ]
    },
    {
      "tipo": "media",
      "circulo": "G",
      "norma": "Reglamento General de Vehículos",
      "articulo": "12",
      "apartado": "5-2",
      "opc": "5A",
      "puntos": "0",
      "importe": "200 €",
      "importe_reducido": "100 €",
      "descripcion": "No colocar **cadenas, dispositivos antideslizantes o neumáticos especiales** cuando sea obligatorio.",
      "tags": [
        "condiciones tecnicas",
        "neumaticos",
        "cadenas",
        "nieve"
      ],
      "nota": "",
      "responsables": [
        "Titular"
      ]
    },
    {
      "tipo": "media",
      "circulo": "G",
      "norma": "Reglamento General de Vehículos",
      "articulo": "12",
      "apartado": "6",
      "opc": "5A",
      "puntos": "0",
      "importe": "200 €",
      "importe_reducido": "100 €",
      "descripcion": "Circular con un vehículo que no esté equipado con protecciones adecuadas que eviten en lo posible las **salpicaduras de las ruedas** (guardabarros).",
      "tags": [
        "condiciones tecnicas",
        "guardabarros",
        "salpicaduras"
      ],
      "nota": "",
      "responsables": [
        "Titular"
      ]
    },
    {
      "tipo": "media",
      "circulo": "G",
      "norma": "Reglamento General de Vehículos",
      "articulo": "12",
      "apartado": "7",
      "opc": "5A",
      "puntos": "0",
      "importe": "200 €",
      "importe_reducido": "100 €",
      "descripcion": "Circular con un vehículo que no dispone de **sistema de suspensión elástica** que facilite la adherencia y la estabilidad.",
      "tags": [
        "condiciones tecnicas",
        "suspension"
      ],
      "nota": "",
      "responsables": [
        "Titular"
      ]
    },
    {
      "tipo": "media",
      "circulo": "G",
      "norma": "Reglamento General de Vehículos",
      "articulo": "12",
      "apartado": "8-1",
      "opc": "5A",
      "puntos": "0",
      "importe": "200 €",
      "importe_reducido": "100 €",
      "descripcion": "Circular con un vehículo que no dispone de un **sistema de frenado** en las condiciones exigidas reglamentariamente.",
      "tags": [
        "condiciones tecnicas",
        "frenos"
      ],
      "nota": "",
      "responsables": [
        "Titular"
      ]
    },
    {
      "tipo": "media",
      "circulo": "G",
      "norma": "Reglamento General de Vehículos",
      "articulo": "12",
      "apartado": "8-4",
      "opc": "5A",
      "puntos": "0",
      "importe": "200 €",
      "importe_reducido": "100 €",
      "descripcion": "Circular con una motocicleta que no dispone de los **sistemas de frenado** establecidos reglamentariamente.",
      "tags": [
        "condiciones tecnicas",
        "frenos",
        "motocicleta"
      ],
      "nota": "Deben tener dos dispositivos, uno para la rueda trasera y otro para la delantera",
      "responsables": [
        "Titular"
      ]
    },
    {
      "tipo": "media",
      "circulo": "G",
      "norma": "Reglamento General de Vehículos",
      "articulo": "12",
      "apartado": "8-5",
      "opc": "5A",
      "puntos": "0",
      "importe": "200 €",
      "importe_reducido": "100 €",
      "descripcion": "Circular con un vehículo de tres ruedas simétricas sin estar equipado de los **sistemas de frenado** reglamentariamente previstos.",
      "tags": [
        "condiciones tecnicas",
        "frenos",
        "tres ruedas"
      ],
      "nota": "",
      "responsables": [
        "Titular"
      ]
    },
    {
      "tipo": "media",
      "circulo": "G",
      "norma": "Reglamento General de Vehículos",
      "articulo": "12",
      "apartado": "9",
      "opc": "5A",
      "puntos": "0",
      "importe": "200 €",
      "importe_reducido": "100 €",
      "descripcion": "Circular con el vehículo reseñado, **sometido a normas especiales**, incumpliendo las exigencias reglamentarias en lo concerniente a sus condiciones técnicas.",
      "tags": [
        "condiciones tecnicas",
        "normas especiales",
        "transporte profesional"
      ],
      "nota": "Vehículos de transporte de viajeros, escolar, mercancías peligrosas, etc",
      "responsables": [
        "Titular"
      ]
    },
    {
      "tipo": "grave",
      "circulo": "MG",
      "norma": "Reglamento General de Vehículos",
      "articulo": "13",
      "apartado": "1",
      "opc": "5A",
      "puntos": "0",
      "importe": "500 €",
      "importe_reducido": "250 €",
      "descripcion": "Circular con un vehículo tractor y su remolque sin que los elementos de **conexión (mecánicos, neumáticos y electrónicos) sean compatibles** entre sí, afectando gravemente a la seguridad vial.",
      "tags": [
        "remolque de vehiculos",
        "acoplamiento",
        "compatibilidad",
        "seguridad vial"
      ],
      "nota": "Posible inmovilización",
      "responsables": [
        "Titular"
      ]
    },
    {
      "tipo": "media",
      "circulo": "G",
      "norma": "Reglamento General de Vehículos",
      "articulo": "13",
      "apartado": "1",
      "opc": "5B",
      "puntos": "0",
      "importe": "200 €",
      "importe_reducido": "100 €",
      "descripcion": "Circular con un vehículo tractor y su remolque **incumpliendo las disposiciones reglamentarias** existentes para estos vehículos.",
      "tags": [
        "remolque de vehiculos",
        "acoplamiento"
      ],
      "nota": "",
      "responsables": [
        "Titular"
      ]
    },
    {
      "tipo": "media",
      "circulo": "G",
      "norma": "Reglamento General de Vehículos",
      "articulo": "13",
      "apartado": "2",
      "opc": "5A",
      "puntos": "0",
      "importe": "200 €",
      "importe_reducido": "100 €",
      "descripcion": "Circular con un remolque que no esté dotado de un dispositivo que obligue a sus ruedas a **seguir una trayectoria análoga** a la del vehículo tractor.",
      "tags": [
        "remolque de vehiculos",
        "trayectoria"
      ],
      "nota": "",
      "responsables": [
        "Titular"
      ]
    },
    {
      "tipo": "media",
      "circulo": "G",
      "norma": "Reglamento General de Vehículos",
      "articulo": "13",
      "apartado": "3",
      "opc": "5A",
      "puntos": "0",
      "importe": "200 €",
      "importe_reducido": "100 €",
      "descripcion": "Circular con un remolque cuyo dispositivo de acoplamiento **no esté dotado con un elemento que impida el desacoplamiento** del mismo.",
      "tags": [
        "remolque de vehiculos",
        "acoplamiento",
        "seguridad"
      ],
      "nota": "",
      "responsables": [
        "Titular"
      ]
    },
    {
      "tipo": "media",
      "circulo": "G",
      "norma": "Reglamento General de Vehículos",
      "articulo": "13",
      "apartado": "4",
      "opc": "5A",
      "puntos": "0",
      "importe": "200 €",
      "importe_reducido": "100 €",
      "descripcion": "Circular con remolque desprovisto de **dispositivo de acoplamiento secundario (cadena, cable, etc.)**.",
      "tags": [
        "remolque de vehiculos",
        "acoplamiento",
        "cadena de seguridad"
      ],
      "nota": "Aplicable a remolques de hasta 1.500 kg de MMA, desprovistos de sistema de frenado automático",
      "responsables": [
        "Titular"
      ]
    },
    {
      "tipo": "media",
      "circulo": "G",
      "norma": "Reglamento General de Vehículos",
      "articulo": "14",
      "apartado": "1",
      "opc": "5B",
      "puntos": "0",
      "importe": "200 €",
      "importe_reducido": "100 €",
      "descripcion": "Circular con un vehículo cuyas **masas, dimensiones y presión sobre el pavimento superen las máximas establecidas**.",
      "tags": [
        "masas y dimensiones",
        "exceso peso",
        "exceso dimensiones"
      ],
      "nota": "Indicar la masa o dimensión antirreglamentaria",
      "responsables": [
        "Titular"
      ]
    },
    {
      "tipo": "grave",
      "circulo": "MG",
      "norma": "Reglamento General de Vehículos",
      "articulo": "14",
      "apartado": "2",
      "opc": "5A",
      "puntos": "0",
      "importe": "500 €",
      "importe_reducido": "250 €",
      "descripcion": "Circular **sin autorización complementaria o especial** con un vehículo que por sus características o por la carga indivisible que transporta supera la longitud, anchura o altura máximas.",
      "tags": [
        "masas y dimensiones",
        "transporte especial",
        "sin autorizacion"
      ],
      "nota": "",
      "responsables": [
        "Titular"
      ]
    },
    {
      "tipo": "grave",
      "circulo": "MG",
      "norma": "Reglamento General de Vehículos",
      "articulo": "14",
      "apartado": "2",
      "opc": "5D",
      "puntos": "0",
      "importe": "500 €",
      "importe_reducido": "250 €",
      "descripcion": "Circular con el vehículo reseñado **incumpliendo las condiciones establecidas en la autorización complementaria o especial**.",
      "tags": [
        "masas y dimensiones",
        "transporte especial",
        "incumplir autorizacion"
      ],
      "nota": "Detallar la condición incumplida",
      "responsables": [
        "Titular",
        "Conductor"
      ]
    },
    {
      "tipo": "media",
      "circulo": "G",
      "norma": "Reglamento General de Vehículos",
      "articulo": "15",
      "apartado": "1",
      "opc": "5A",
      "puntos": "0",
      "importe": "200 €",
      "importe_reducido": "100 €",
      "descripcion": "Circular con un vehículo cuyas **luces y dispositivos reflectantes dobles no se correspondan en color, intensidad y colocación** a las establecidas reglamentariamente.",
      "tags": [
        "alumbrado",
        "condiciones tecnicas",
        "luces",
        "reflectantes"
      ],
      "nota": "",
      "responsables": [
        "Titular"
      ]
    },
    {
      "tipo": "media",
      "circulo": "G",
      "norma": "Reglamento General de Vehículos",
      "articulo": "15",
      "apartado": "2",
      "opc": "5A",
      "puntos": "0",
      "importe": "200 €",
      "importe_reducido": "100 €",
      "descripcion": "Circular con el vehículo reseñado teniendo instaladas en el mismo **más luces intermitentes o de intensidad variable** de las indicadas reglamentariamente.",
      "tags": [
        "alumbrado",
        "condiciones tecnicas",
        "luces no autorizadas"
      ],
      "nota": "",
      "responsables": [
        "Titular"
      ]
    },
    {
      "tipo": "media",
      "circulo": "G",
      "norma": "Reglamento General de Vehículos",
      "articulo": "15",
      "apartado": "4",
      "opc": "5B",
      "puntos": "0",
      "importe": "200 €",
      "importe_reducido": "100 €",
      "descripcion": "Circular con un vehículo cuyos dispositivos de **alumbrado y señalización óptica no cumplan las exigencias** especificadas en la reglamentación.",
      "tags": [
        "alumbrado",
        "condiciones tecnicas",
        "luces",
        "señalizacion"
      ],
      "nota": "Por ejemplo, llevar láminas plásticas que oscurecen los pilotos",
      "responsables": [
        "Titular"
      ]
    },
    {
      "tipo": "media",
      "circulo": "G",
      "norma": "Reglamento General de Vehículos",
      "articulo": "15",
      "apartado": "5",
      "opc": "5A",
      "puntos": "0",
      "importe": "200 €",
      "importe_reducido": "100 €",
      "descripcion": "Circular con el vehículo reseñado llevando instaladas **más luces que las reglamentariamente admitidas**.",
      "tags": [
        "alumbrado",
        "condiciones tecnicas",
        "luces no autorizadas"
      ],
      "nota": "Por ejemplo, una tira de luces LED en el paragolpes",
      "responsables": [
        "Titular"
      ]
    },
    {
      "tipo": "media",
      "circulo": "G",
      "norma": "Reglamento General de Vehículos",
      "articulo": "15",
      "apartado": "5",
      "opc": "5B",
      "puntos": "0",
      "importe": "200 €",
      "importe_reducido": "100 €",
      "descripcion": "Circular con el vehículo reseñado llevando **dispositivos reflectantes o pinturas no autorizados**.",
      "tags": [
        "alumbrado",
        "condiciones tecnicas",
        "reflectantes no autorizados"
      ],
      "nota": "",
      "responsables": [
        "Titular"
      ]
    },
    {
      "tipo": "media",
      "circulo": "G",
      "norma": "Reglamento General de Vehículos",
      "articulo": "15",
      "apartado": "5",
      "opc": "5C",
      "puntos": "0",
      "importe": "200 €",
      "importe_reducido": "100 €",
      "descripcion": "Circular con el vehículo reseñado llevando instalados **dispositivos luminosos no autorizados**.",
      "tags": [
        "alumbrado",
        "condiciones tecnicas",
        "luces no autorizadas"
      ],
      "nota": "Por ejemplo, luces de neón en los bajos",
      "responsables": [
        "Titular"
      ]
    },
    {
      "tipo": "media",
      "circulo": "G",
      "norma": "Reglamento General de Vehículos",
      "articulo": "16",
      "apartado": "-",
      "opc": "5A",
      "puntos": "0",
      "importe": "200 €",
      "importe_reducido": "100 €",
      "descripcion": "Circular con el vehículo reseñado sin estar provisto de los **dispositivos de alumbrado y señalización óptica obligatorios**.",
      "tags": [
        "alumbrado",
        "condiciones tecnicas",
        "luces obligatorias"
      ],
      "nota": "Deberá especificarse el dispositivo del que carece. También aplicable si están fracturados o han perdido su eficacia",
      "responsables": [
        "Titular"
      ]
    },
    {
      "tipo": "media",
      "circulo": "G",
      "norma": "Reglamento General de Vehículos",
      "articulo": "17",
      "apartado": "-",
      "opc": "5A",
      "puntos": "0",
      "importe": "200 €",
      "importe_reducido": "100 €",
      "descripcion": "Circular con el vehículo reseñado estando provisto de **dispositivos de alumbrado y señalización óptica no autorizados** reglamentariamente.",
      "tags": [
        "alumbrado",
        "condiciones tecnicas",
        "luces no autorizadas"
      ],
      "nota": "Especificar el dispositivo instalado",
      "responsables": [
        "Titular"
      ]
    },
    {
      "tipo": "leve",
      "circulo": "L",
      "norma": "Reglamento General de Vehículos",
      "articulo": "18",
      "apartado": "1",
      "opc": "5B",
      "puntos": "0",
      "importe": "80 €",
      "importe_reducido": "40 €",
      "descripcion": "No llevar instalada en el vehículo la **señal reglamentaria correspondiente** (V-1, V-2, etc.).",
      "tags": [
        "señalizacion",
        "señales en vehiculos"
      ],
      "nota": "Deberá indicarse la señal omitida",
      "responsables": [
        "Titular",
        "Conductor"
      ]
    },
    {
      "tipo": "leve",
      "circulo": "L",
      "norma": "Reglamento General de Vehículos",
      "articulo": "18",
      "apartado": "1",
      "opc": "5C",
      "puntos": "0",
      "importe": "80 €",
      "importe_reducido": "40 €",
      "descripcion": "Circular con el vehículo reseñado teniendo instalada la **señal V-14 (prácticas)** sin encontrarse en el momento de los hechos realizando o ejerciendo las funciones reglamentariamente establecidas.",
      "tags": [
        "señalizacion",
        "señal v-14",
        "autoescuela"
      ],
      "nota": "",
      "responsables": [
        "Conductor"
      ]
    },
    {
      "tipo": "grave",
      "circulo": "MG",
      "norma": "Reglamento General de Vehículos",
      "articulo": "18",
      "apartado": "1",
      "opc": "5D",
      "puntos": "0",
      "importe": "500 €",
      "importe_reducido": "250 €",
      "descripcion": "Circular con el vehículo reseñado teniendo instalados **dispositivos luminosos de señales especiales (V-1, V-2)** teniéndolo específicamente prohibido.",
      "tags": [
        "señalizacion",
        "luces no autorizadas",
        "señal v-1",
        "señal v-2"
      ],
      "nota": "",
      "responsables": [
        "Titular"
      ]
    },
    {
      "tipo": "leve",
      "circulo": "L",
      "norma": "Reglamento General de Vehículos",
      "articulo": "18",
      "apartado": "1",
      "opc": "5E",
      "puntos": "0",
      "importe": "80 €",
      "importe_reducido": "40 €",
      "descripcion": "Circular con el vehículo reseñado teniendo instaladas señales... **no ajustándose a lo dispuesto reglamentariamente**.",
      "tags": [
        "señalizacion",
        "señales en vehiculos"
      ],
      "nota": "Tipo genérico para el resto de señales del Anexo XI",
      "responsables": [
        "Titular",
        "Conductor"
      ]
    },
    {
      "tipo": "leve",
      "circulo": "L",
      "norma": "Reglamento General de Vehículos",
      "articulo": "19",
      "apartado": "1",
      "opc": "5C",
      "puntos": "0",
      "importe": "80 €",
      "importe_reducido": "40 €",
      "descripcion": "Circular con el vehículo reseñado **sin llevar los accesorios, repuestos y/o herramientas**, establecidos reglamentariamente.",
      "tags": [
        "condiciones tecnicas",
        "accesorios",
        "repuestos",
        "chaleco",
        "triangulos"
      ],
      "nota": "Dispositivo V-16 (o triángulos hasta 2026), chaleco reflectante y rueda de repuesto o sistema alternativo",
      "responsables": [
        "Titular"
      ]
    },
    {
      "tipo": "media",
      "circulo": "G",
      "norma": "Reglamento General de Vehículos",
      "articulo": "21",
      "apartado": "1",
      "opc": "5B",
      "puntos": "0",
      "importe": "200 €",
      "importe_reducido": "100 €",
      "descripcion": "Circular con el **ciclomotor** reseñado que **carece de espejo retrovisor**.",
      "tags": [
        "ciclomotores",
        "condiciones tecnicas",
        "espejo retrovisor"
      ],
      "nota": "Obligatorio uno izquierdo, o izquierdo e interior si tiene carrocería",
      "responsables": [
        "Titular"
      ]
    },
    {
      "tipo": "media",
      "circulo": "G",
      "norma": "Reglamento General de Vehículos",
      "articulo": "21",
      "apartado": "1",
      "opc": "5C",
      "puntos": "0",
      "importe": "200 €",
      "importe_reducido": "100 €",
      "descripcion": "Circular con un **ciclomotor que no se ajusta a los tipos de homologación** y características técnicas reglamentariamente establecidas.",
      "tags": [
        "ciclomotores",
        "condiciones tecnicas",
        "homologacion"
      ],
      "nota": "",
      "responsables": [
        "Titular",
        "Conductor"
      ]
    },
    {
      "tipo": "media",
      "circulo": "G",
      "norma": "Reglamento General de Vehículos",
      "articulo": "21",
      "apartado": "2",
      "opc": "5A",
      "puntos": "0",
      "importe": "200 €",
      "importe_reducido": "100 €",
      "descripcion": "Circular con el **ciclomotor** reseñado sin estar provisto de **alumbrado y señalización óptica obligatorios**.",
      "tags": [
        "ciclomotores",
        "condiciones tecnicas",
        "alumbrado"
      ],
      "nota": "Especificar el incumplimiento",
      "responsables": [
        "Titular",
        "Conductor"
      ]
    },
    {
      "tipo": "leve",
      "circulo": "L",
      "norma": "Reglamento General de Vehículos",
      "articulo": "22",
      "apartado": "1",
      "opc": "5A",
      "puntos": "0",
      "importe": "80 €",
      "importe_reducido": "40 €",
      "descripcion": "Circular con un ciclo **sin un sistema adecuado de frenado**.",
      "tags": [
        "ciclos",
        "bicicleta",
        "condiciones tecnicas",
        "frenos"
      ],
      "nota": "Debe actuar sobre las ruedas delanteras y traseras",
      "responsables": [
        "Conductor"
      ]
    },
    {
      "tipo": "leve",
      "circulo": "L",
      "norma": "Reglamento General de Vehículos",
      "articulo": "22",
      "apartado": "1",
      "opc": "5B",
      "puntos": "0",
      "importe": "80 €",
      "importe_reducido": "40 €",
      "descripcion": "Circular con un ciclo **desprovisto de timbre**.",
      "tags": [
        "ciclos",
        "bicicleta",
        "condiciones tecnicas",
        "timbre"
      ],
      "nota": "Se prohíbe otro dispositivo acústico distinto",
      "responsables": [
        "Conductor"
      ]
    },
    {
      "tipo": "media",
      "circulo": "G",
      "norma": "Reglamento General de Vehículos",
      "articulo": "22",
      "apartado": "2",
      "opc": "5A",
      "puntos": "0",
      "importe": "200 €",
      "importe_reducido": "100 €",
      "descripcion": "Circular de **noche** con un ciclo o por tramo de vía señalizado como túnel, **sin disponer de las luces y catadióptricos** reglamentariamente establecidos.",
      "tags": [
        "ciclos",
        "condiciones tecnicas",
        "alumbrado",
        "luces",
        "catadioptricos"
      ],
      "nota": "No aplicable a bicicletas (que tienen su propio precepto)",
      "responsables": [
        "Conductor"
      ]
    },
    {
      "tipo": "media",
      "circulo": "G",
      "norma": "Reglamento General de Vehículos",
      "articulo": "22",
      "apartado": "2",
      "opc": "5B",
      "puntos": "0",
      "importe": "200 €",
      "importe_reducido": "100 €",
      "descripcion": "Circular con un ciclo en **condiciones meteorológicas que disminuyan sensiblemente la visibilidad**, sin disponer de las luces y catadióptricos reglamentarios.",
      "tags": [
        "ciclos",
        "condiciones tecnicas",
        "alumbrado",
        "visibilidad reducida"
      ],
      "nota": "No aplicable a bicicletas",
      "responsables": [
        "Conductor"
      ]
    },
    {
      "tipo": "media",
      "circulo": "G",
      "norma": "Reglamento General de Vehículos",
      "articulo": "22",
      "apartado": "4",
      "opc": "5A",
      "puntos": "0",
      "importe": "200 €",
      "importe_reducido": "100 €",
      "descripcion": "Circular con una **bicicleta de noche** o por tramo señalizado con la señal de túnel, **sin disponer de las luces y catadióptricos** reglamentariamente establecidos.",
      "tags": [
        "ciclos",
        "bicicleta",
        "condiciones tecnicas",
        "alumbrado"
      ],
      "nota": "Luz de posición delantera/trasera y catadióptrico trasero",
      "responsables": [
        "Conductor"
      ]
    },
    {
      "tipo": "media",
      "circulo": "G",
      "norma": "Reglamento General de Vehículos",
      "articulo": "22",
      "apartado": "4",
      "opc": "5B",
      "puntos": "0",
      "importe": "200 €",
      "importe_reducido": "100 €",
      "descripcion": "Circular con una **bicicleta en condiciones meteorológicas que disminuyen sensiblemente la visibilidad**, sin disponer de las luces y catadióptricos reglamentarios.",
      "tags": [
        "ciclos",
        "bicicleta",
        "condiciones tecnicas",
        "alumbrado",
        "visibilidad reducida"
      ],
      "nota": "",
      "responsables": [
        "Conductor"
      ]
    },
    {
      "tipo": "leve",
      "circulo": "L",
      "norma": "Reglamento General de Vehículos",
      "articulo": "23",
      "apartado": "-",
      "opc": "5A",
      "puntos": "0",
      "importe": "80 €",
      "importe_reducido": "40 €",
      "descripcion": "Circular con un **vehículo de tracción animal sin ajustarse a las condiciones exigidas** reglamentariamente.",
      "tags": [
        "circulacion de animales",
        "traccion animal",
        "condiciones tecnicas"
      ],
      "nota": "Ruedas neumáticas, alumbrado nocturno, etc",
      "responsables": [
        "Conductor"
      ]
    },
    {
      "tipo": "media",
      "circulo": "G",
      "norma": "Reglamento General de Vehículos",
      "articulo": "24",
      "apartado": "-",
      "opc": "5A",
      "puntos": "0",
      "importe": "200 €",
      "importe_reducido": "100 €",
      "descripcion": "Circular con el **tranvía** reseñado sin llevar los **dispositivos de alumbrado** en la forma y condiciones establecidos reglamentariamente.",
      "tags": [
        "tranvias",
        "alumbrado",
        "condiciones tecnicas"
      ],
      "nota": "",
      "responsables": [
        "Titular"
      ]
    },
    {
      "tipo": "media",
      "circulo": "G",
      "norma": "Reglamento General de Vehículos",
      "articulo": "25",
      "apartado": "1",
      "opc": "5A",
      "puntos": "0",
      "importe": "200 €",
      "importe_reducido": "100 €",
      "descripcion": "Poner en circulación un vehículo a motor, remolque o semirremolque, **sin llevar las placas de matrícula** en la forma establecida reglamentariamente.",
      "tags": [
        "placas",
        "matricula",
        "remolque"
      ],
      "nota": "",
      "responsables": [
        "Titular",
        "Conductor"
      ]
    },
    {
      "tipo": "media",
      "circulo": "G",
      "norma": "Reglamento General de Vehículos",
      "articulo": "25",
      "apartado": "1",
      "opc": "5B",
      "puntos": "0",
      "importe": "200 €",
      "importe_reducido": "100 €",
      "descripcion": "Poner en circulación un **ciclomotor, sin llevar las placas de matrícula** en la forma establecida reglamentariamente.",
      "tags": [
        "placas",
        "matricula",
        "ciclomotor"
      ],
      "nota": "",
      "responsables": [
        "Titular",
        "Conductor"
      ]
    },
    {
      "tipo": "grave",
      "circulo": "MG",
      "norma": "Reglamento General de Vehículos",
      "articulo": "28",
      "apartado": "6",
      "opc": "5A",
      "puntos": "0",
      "importe": "500 €",
      "importe_reducido": "250 €",
      "descripcion": "Circular con un **tren turístico sin haber obtenido una autorización complementaria** de circulación por parte del órgano competente.",
      "tags": [
        "carencia aut. para circular",
        "tren turistico"
      ],
      "nota": "En vías urbanas, la autorización la expide el ayuntamiento",
      "responsables": [
        "Titular"
      ]
    },
    {
      "tipo": "leve",
      "circulo": "L",
      "norma": "Reglamento General de Vehículos",
      "articulo": "30",
      "apartado": "1",
      "opc": "5A",
      "puntos": "0",
      "importe": "80 €",
      "importe_reducido": "40 €",
      "descripcion": "Circular con el vehículo reseñado, **llevando el original del permiso o licencia de circulación, una vez expedido duplicado** del mismo por extravío o sustracción.",
      "tags": [
        "documentacion",
        "permiso de circulacion",
        "duplicado"
      ],
      "nota": "",
      "responsables": [
        "Conductor"
      ]
    },
    {
      "tipo": "leve",
      "circulo": "L",
      "norma": "Reglamento General de Vehículos",
      "articulo": "30",
      "apartado": "2",
      "opc": "5A",
      "puntos": "0",
      "importe": "80 €",
      "importe_reducido": "40 €",
      "descripcion": "Circular con el vehículo reseñado sin haber **renovado el permiso o licencia de circulación**, habiéndose producido **variaciones en los datos personales** del titular del mismo.",
      "tags": [
        "documentacion",
        "permiso de circulacion",
        "renovacion",
        "datos personales"
      ],
      "nota": "Plazo de 15 días desde la variación",
      "responsables": [
        "Titular"
      ]
    },
    {
      "tipo": "media",
      "circulo": "G",
      "norma": "Reglamento General de Vehículos",
      "articulo": "30",
      "apartado": "2",
      "opc": "5C",
      "puntos": "0",
      "importe": "200 €",
      "importe_reducido": "100 €",
      "descripcion": "Circular con el vehículo reseñado sin haber **renovado el permiso o licencia de circulación**, habiéndose **cambiado el destino del mismo o modificado alguna característica** hecha constar en dicho documento.",
      "tags": [
        "documentacion",
        "permiso de circulacion",
        "renovacion",
        "modificacion caracteristicas"
      ],
      "nota": "",
      "responsables": [
        "Titular"
      ]
    },
    {
      "tipo": "media",
      "circulo": "G",
      "norma": "Reglamento General de Vehículos",
      "articulo": "31",
      "apartado": "-",
      "opc": "5A",
      "puntos": "0",
      "importe": "200 €",
      "importe_reducido": "100 €",
      "descripcion": "Circular con el vehículo reseñado sin haber renovado el permiso o licencia de circulación, habiendo **variado la titularidad registral** del mismo.",
      "tags": [
        "documentacion",
        "cambio de titularidad",
        "transferencia"
      ],
      "nota": "Aplicable a vehículos con notificaciones de venta",
      "responsables": [
        "Titular"
      ]
    },
    {
      "tipo": "leve",
      "circulo": "L",
      "norma": "Reglamento General de Vehículos",
      "articulo": "32",
      "apartado": "1",
      "opc": "5B",
      "puntos": "0",
      "importe": "80 €",
      "importe_reducido": "40 €",
      "descripcion": "**No haber notificado a la Jefatura de Tráfico la transmisión** de su vehículo a otra persona en el plazo reglamentariamente establecido.",
      "tags": [
        "documentacion",
        "notificacion de venta"
      ],
      "nota": "El plazo es de 10 días desde la transmisión",
      "responsables": [
        "Titular"
      ]
    },
    {
      "tipo": "media",
      "circulo": "G",
      "norma": "Reglamento General de Vehículos",
      "articulo": "32",
      "apartado": "3",
      "opc": "5D",
      "puntos": "0",
      "importe": "200 €",
      "importe_reducido": "100 €",
      "descripcion": "**No haber solicitado el adquirente** del vehículo reseñado la **renovación del permiso o licencia de circulación**, dentro del plazo reglamentariamente establecido.",
      "tags": [
        "documentacion",
        "cambio de titularidad",
        "adquirente"
      ],
      "nota": "El plazo es de 30 días desde la adquisición. Posible inmovilización",
      "responsables": [
        "Titular",
        "Conductor"
      ]
    },
    {
      "tipo": "media",
      "circulo": "G",
      "norma": "Reglamento General de Vehículos",
      "articulo": "32",
      "apartado": "6",
      "opc": "5B",
      "puntos": "0",
      "importe": "200 €",
      "importe_reducido": "100 €",
      "descripcion": "No haber solicitado en el plazo reglamentario el **adjudicatario definitivo por herencia** la expedición a su nombre del nuevo permiso o licencia de circulación.",
      "tags": [
        "documentacion",
        "cambio de titularidad",
        "herencia"
      ],
      "nota": "El plazo es de 90 días desde la adjudicación",
      "responsables": [
        "Titular",
        "Conductor"
      ]
    },
    {
      "tipo": "media",
      "circulo": "G",
      "norma": "Reglamento General de Vehículos",
      "articulo": "32",
      "apartado": "6",
      "opc": "5C",
      "puntos": "0",
      "importe": "200 €",
      "importe_reducido": "100 €",
      "descripcion": "No haber notificado la persona que tenga a su cargo la custodia o uso del vehículo, registrado a nombre de una **persona fallecida**, dicha circunstancia a la Jefatura de Tráfico.",
      "tags": [
        "documentacion",
        "fallecimiento titular"
      ],
      "nota": "El plazo es de 90 días desde el fallecimiento",
      "responsables": [
        "Conductor"
      ]
    },
    {
      "tipo": "leve",
      "circulo": "L",
      "norma": "Reglamento General de Vehículos",
      "articulo": "33",
      "apartado": "1",
      "opc": "5B",
      "puntos": "0",
      "importe": "80 €",
      "importe_reducido": "40 €",
      "descripcion": "No haber solicitado en plazo la **baja temporal** del vehículo de su titularidad, una vez entregado para su posterior transmisión, a un vendedor de vehículos.",
      "tags": [
        "carencia aut. para circular",
        "baja temporal",
        "compraventa"
      ],
      "nota": "El plazo es de 10 días desde la entrega",
      "responsables": [
        "Titular"
      ]
    },
    {
      "tipo": "media",
      "circulo": "G",
      "norma": "Reglamento General de Vehículos",
      "articulo": "33",
      "apartado": "2",
      "opc": "5A",
      "puntos": "0",
      "importe": "200 €",
      "importe_reducido": "100 €",
      "descripcion": "Circular con un vehículo **dado de baja temporal por transferencia**, sin estar amparado por un permiso y placas temporales de empresa.",
      "tags": [
        "carencia aut. para circular",
        "baja temporal",
        "placas temporales"
      ],
      "nota": "Posible inmovilización",
      "responsables": [
        "Titular"
      ]
    },
    {
      "tipo": "media",
      "circulo": "G",
      "norma": "Reglamento General de Vehículos",
      "articulo": "33",
      "apartado": "3",
      "opc": "5A",
      "puntos": "0",
      "importe": "200 €",
      "importe_reducido": "100 €",
      "descripcion": "Circular con el vehículo, habiendo sido adquirido por compraventa, **sin haber solicitado la inscripción del mismo a su nombre** en el plazo máximo.",
      "tags": [
        "carencia aut. para circular",
        "cambio de titularidad",
        "compraventa"
      ],
      "nota": "El plazo es de 30 días. Posible inmovilización",
      "responsables": [
        "Titular"
      ]
    },
    {
      "tipo": "media",
      "circulo": "G",
      "norma": "Reglamento General de Vehículos",
      "articulo": "33",
      "apartado": "6",
      "opc": "5A",
      "puntos": "0",
      "importe": "200 €",
      "importe_reducido": "100 €",
      "descripcion": "No haber solicitado el titular de un establecimiento de compraventa de vehículos, el **cambio de titularidad del vehículo a su nombre, una vez transcurrido el plazo de un año** desde que se produjo la baja temporal del mismo.",
      "tags": [
        "carencia aut. para circular",
        "cambio de titularidad",
        "compraventa"
      ],
      "nota": "",
      "responsables": [
        "Titular"
      ]
    },
    {
      "tipo": "grave",
      "circulo": "MG",
      "norma": "Reglamento General de Vehículos",
      "articulo": "34",
      "apartado": "-",
      "opc": "5A",
      "puntos": "0",
      "importe": "500 €",
      "importe_reducido": "250 €",
      "descripcion": "Circular con el vehículo, cuyo permiso o licencia de circulación ha perdido su vigencia, habiendo **causado baja** el mismo en el registro de vehículos.",
      "tags": [
        "carencia aut. para circular",
        "dado de baja",
        "baja definitiva"
      ],
      "nota": "Posible inmovilización",
      "responsables": [
        "Titular",
        "Conductor"
      ]
    },
    {
      "tipo": "grave",
      "circulo": "MG",
      "norma": "Reglamento General de Vehículos",
      "articulo": "34",
      "apartado": "-",
      "opc": "5B",
      "puntos": "0",
      "importe": "500 €",
      "importe_reducido": "250 €",
      "descripcion": "Circular con el vehículo, cuyo permiso o licencia ha perdido su vigencia, una vez comprobado que **no es apto para la circulación**.",
      "tags": [
        "carencia aut. para circular",
        "no apto",
        "itv negativa"
      ],
      "nota": "Ej. tras ITV negativa o iniciado procedimiento de residuo. Posible inmovilización",
      "responsables": [
        "Conductor"
      ]
    },
    {
      "tipo": "media",
      "circulo": "G",
      "norma": "Reglamento General de Vehículos",
      "articulo": "40",
      "apartado": "4",
      "opc": "5A",
      "puntos": "0",
      "importe": "200 €",
      "importe_reducido": "100 €",
      "descripcion": "Circular con el vehículo habiendo **caducado el plazo de validez de la matrícula turística** que ostenta, sin haber obtenido prórroga.",
      "tags": [
        "carencia aut. para circular",
        "matricula turistica",
        "plazo caducado"
      ],
      "nota": "La caducidad del permiso conlleva el precintado y depósito del vehículo",
      "responsables": [
        "Titular"
      ]
    },
    {
      "tipo": "grave",
      "circulo": "MG",
      "norma": "Reglamento General de Vehículos",
      "articulo": "42",
      "apartado": "1",
      "opc": "5A",
      "puntos": "0",
      "importe": "500 €",
      "importe_reducido": "250 €",
      "descripcion": "Poner en circulación el vehículo reseñado **sin haber obtenido el permiso temporal** correspondiente que autorice su circulación provisional.",
      "tags": [
        "carencia aut. para circular",
        "permiso temporal",
        "placas provisionales"
      ],
      "nota": "Posible inmovilización",
      "responsables": [
        "Titular",
        "Conductor"
      ]
    },
    {
      "tipo": "media",
      "circulo": "G",
      "norma": "Reglamento General de Vehículos",
      "articulo": "42",
      "apartado": "1",
      "opc": "5H",
      "puntos": "0",
      "importe": "200 €",
      "importe_reducido": "100 €",
      "descripcion": "Poner en circulación el vehículo reseñado teniendo el **permiso temporal... caducado**.",
      "tags": [
        "carencia aut. para circular",
        "permiso temporal",
        "placas provisionales",
        "caducado"
      ],
      "nota": "Posible inmovilización",
      "responsables": [
        "Titular",
        "Conductor"
      ]
    },
    {
      "tipo": "leve",
      "circulo": "L",
      "norma": "Reglamento General de Vehículos",
      "articulo": "42",
      "apartado": "2",
      "opc": "5A",
      "puntos": "0",
      "importe": "80 €",
      "importe_reducido": "40 €",
      "descripcion": "Poner en circulación el vehículo al amparo de un permiso temporal de circulación provisional, **sin ajustarse a las prescripciones establecidas** reglamentariamente.",
      "tags": [
        "carencia aut. para circular",
        "permiso temporal",
        "incumplir condiciones"
      ],
      "nota": "",
      "responsables": [
        "Titular",
        "Conductor"
      ]
    },
    {
      "tipo": "media",
      "circulo": "G",
      "norma": "Reglamento General de Vehículos",
      "articulo": "45",
      "apartado": "1",
      "opc": "5B",
      "puntos": "0",
      "importe": "200 €",
      "importe_reducido": "100 €",
      "descripcion": "Poner en circulación el vehículo, amparado en un permiso temporal, **sin llevar... el correspondiente boletín de circulación**, careciendo de validez.",
      "tags": [
        "carencia aut. para circular",
        "boletin de circulacion",
        "placas S"
      ],
      "nota": "Placas con distintivo 'S'",
      "responsables": [
        "Titular",
        "Conductor"
      ]
    },
    {
      "tipo": "media",
      "circulo": "G",
      "norma": "Reglamento General de Vehículos",
      "articulo": "46",
      "apartado": "1",
      "opc": "5A",
      "puntos": "0",
      "importe": "200 €",
      "importe_reducido": "100 €",
      "descripcion": "Poner en circulación el vehículo, amparado en un permiso temporal de empresa, **incumpliendo las condiciones técnicas** prescritas en el mismo.",
      "tags": [
        "carencia aut. para circular",
        "permiso temporal",
        "condiciones tecnicas"
      ],
      "nota": "",
      "responsables": [
        "Titular"
      ]
    },
    {
      "tipo": "leve",
      "circulo": "L",
      "norma": "Reglamento General de Vehículos",
      "articulo": "46",
      "apartado": "2",
      "opc": "5C",
      "puntos": "0",
      "importe": "80 €",
      "importe_reducido": "40 €",
      "descripcion": "Poner en circulación el vehículo, siendo conducido por **persona distinta al titular del permiso temporal** o persona a su servicio.",
      "tags": [
        "documentacion",
        "permiso temporal",
        "placas S"
      ],
      "nota": "Placa 'S'",
      "responsables": [
        "Titular"
      ]
    },
    {
      "tipo": "leve",
      "circulo": "L",
      "norma": "Reglamento General de Vehículos",
      "articulo": "46",
      "apartado": "2",
      "opc": "5D",
      "puntos": "0",
      "importe": "80 €",
      "importe_reducido": "40 €",
      "descripcion": "Poner en circulación el vehículo, al amparo de un permiso o placa temporal, siendo **ocupado por persona o número de personas distintas** a las establecidas.",
      "tags": [
        "documentacion",
        "permiso temporal",
        "exceso ocupacion"
      ],
      "nota": "",
      "responsables": [
        "Titular"
      ]
    },
    {
      "tipo": "media",
      "circulo": "G",
      "norma": "Reglamento General de Vehículos",
      "articulo": "46",
      "apartado": "3",
      "opc": "5B",
      "puntos": "0",
      "importe": "200 €",
      "importe_reducido": "100 €",
      "descripcion": "Poner en circulación el vehículo, al amparo de un permiso, boletín o placa temporal de empresa, utilizándolo para **fines distintos a los establecidos**.",
      "tags": [
        "carencia aut. para circular",
        "permiso temporal",
        "uso indebido"
      ],
      "nota": "Placas 'S' y 'V'. El permiso puede quedar en suspenso",
      "responsables": [
        "Titular"
      ]
    },
    {
      "tipo": "media",
      "circulo": "G",
      "norma": "Reglamento General de Vehículos",
      "articulo": "46",
      "apartado": "3",
      "opc": "5C",
      "puntos": "0",
      "importe": "200 €",
      "importe_reducido": "100 €",
      "descripcion": "Poner en circulación el vehículo, al amparo de un permiso, boletín o placa temporal de empresa, **llevando en el mismo carga útil**.",
      "tags": [
        "carencia aut. para circular",
        "permiso temporal",
        "carga util"
      ],
      "nota": "Placas 'S' y 'V'",
      "responsables": [
        "Titular"
      ]
    },
    {
      "tipo": "grave",
      "circulo": "MG",
      "norma": "Reglamento General de Vehículos",
      "articulo": "48",
      "apartado": "2",
      "opc": "5A",
      "puntos": "0",
      "importe": "500 €",
      "importe_reducido": "250 €",
      "descripcion": "Poner en circulación el vehículo reseñado teniendo el **permiso temporal para vehículos ya matriculados (placa 'V') caducado**.",
      "tags": [
        "carencia aut. para circular",
        "permiso temporal",
        "placas V",
        "caducado"
      ],
      "nota": "Posible inmovilización",
      "responsables": [
        "Titular",
        "Conductor"
      ]
    },
    {
      "tipo": "media",
      "circulo": "G",
      "norma": "Reglamento General de Vehículos",
      "articulo": "48",
      "apartado": "4",
      "opc": "5C",
      "puntos": "0",
      "importe": "200 €",
      "importe_reducido": "100 €",
      "descripcion": "Poner en circulación el vehículo reseñado, amparado en un permiso temporal (placa 'V'), **sin llevar el correspondiente boletín de circulación**.",
      "tags": [
        "carencia aut. para circular",
        "permiso temporal",
        "placas V",
        "boletin de circulacion"
      ],
      "nota": "",
      "responsables": [
        "Titular"
      ]
    },
    {
      "tipo": "leve",
      "circulo": "L",
      "norma": "Reglamento General de Vehículos",
      "articulo": "48",
      "apartado": "4",
      "opc": "5D",
      "puntos": "0",
      "importe": "80 €",
      "importe_reducido": "40 €",
      "descripcion": "Poner en circulación el vehículo, al amparo de un permiso o placa temporal (placa 'V'), siendo **ocupado por persona o número de personas distintas** a las establecidas.",
      "tags": [
        "documentacion",
        "permiso temporal",
        "placas V",
        "exceso ocupacion"
      ],
      "nota": "",
      "responsables": [
        "Titular"
      ]
    },
    {
      "tipo": "media",
      "circulo": "G",
      "norma": "Reglamento General de Vehículos",
      "articulo": "49",
      "apartado": "1",
      "opc": "5A",
      "puntos": "0",
      "importe": "200 €",
      "importe_reducido": "100 €",
      "descripcion": "Circular con el vehículo cuyas **placas de matrícula no se corresponden a tipos homologados**, teniendo unas dimensiones y caracteres distintos a los reglamentarios.",
      "tags": [
        "placas",
        "matricula no homologada"
      ],
      "nota": "",
      "responsables": [
        "Titular"
      ]
    },
    {
      "tipo": "media",
      "circulo": "G",
      "norma": "Reglamento General de Vehículos",
      "articulo": "49",
      "apartado": "1",
      "opc": "5B",
      "puntos": "0",
      "importe": "200 €",
      "importe_reducido": "100 €",
      "descripcion": "Circular con el vehículo cuyas placas de matrícula **no conservan su poder retrorreflectante, no siendo visibles y legibles**.",
      "tags": [
        "placas",
        "matricula ilegible",
        "reflectante"
      ],
      "nota": "Aplicable a la pérdida de visibilidad sin que exista un obstáculo añadido",
      "responsables": [
        "Titular"
      ]
    },
    {
      "tipo": "media",
      "circulo": "G",
      "norma": "Reglamento General de Vehículos",
      "articulo": "49",
      "apartado": "1",
      "opc": "5C",
      "puntos": "0",
      "importe": "200 €",
      "importe_reducido": "100 €",
      "descripcion": "Circular el vehículo incumpliendo el anexo XVIII del RGV, **no siendo conforme sus placas a los requisitos técnicos** establecidos.",
      "tags": [
        "placas",
        "requisitos tecnicos"
      ],
      "nota": "",
      "responsables": [
        "Titular"
      ]
    },
    {
      "tipo": "media",
      "circulo": "G",
      "norma": "Reglamento General de Vehículos",
      "articulo": "49",
      "apartado": "2",
      "opc": "5C",
      "puntos": "0",
      "importe": "200 €",
      "importe_reducido": "100 €",
      "descripcion": "Incumplir (Grave) el titular de un **establecimiento de manipulación y/o expedición de placas de matrícula** las normas reglamentarias.",
      "tags": [
        "placas",
        "manipulador",
        "establecimiento"
      ],
      "nota": "",
      "responsables": [
        "Titular"
      ]
    },
    {
      "tipo": "leve",
      "circulo": "L",
      "norma": "Reglamento General de Vehículos",
      "articulo": "49",
      "apartado": "2",
      "opc": "5D",
      "puntos": "0",
      "importe": "80 €",
      "importe_reducido": "40 €",
      "descripcion": "Incumplir (Leve) el titular de un **establecimiento de manipulación y/o expedición de placas de matrícula** las normas reglamentarias.",
      "tags": [
        "placas",
        "manipulador",
        "establecimiento"
      ],
      "nota": "",
      "responsables": [
        "Titular"
      ]
    },
    {
      "tipo": "leve",
      "circulo": "L",
      "norma": "Reglamento General de Vehículos",
      "articulo": "49",
      "apartado": "3",
      "opc": "5A",
      "puntos": "0",
      "importe": "80 €",
      "importe_reducido": "40 €",
      "descripcion": "Incumplir el **fabricante** de placas de matrícula la obligación de que **aparezca su nombre o marca registrada** en la forma reglamentaria.",
      "tags": [
        "placas",
        "fabricante"
      ],
      "nota": "",
      "responsables": [
        "Titular"
      ]
    },
    {
      "tipo": "media",
      "circulo": "G",
      "norma": "Reglamento General de Vehículos",
      "articulo": "49",
      "apartado": "4",
      "opc": "5A",
      "puntos": "0",
      "importe": "200 €",
      "importe_reducido": "100 €",
      "descripcion": "Circular con el vehículo cuyas placas de matrícula tienen **incorporados signos u otros caracteres distintos** a los señalados reglamentariamente.",
      "tags": [
        "placas",
        "manipulacion",
        "caracteres no autorizados"
      ],
      "nota": "",
      "responsables": [
        "Titular"
      ]
    },
    {
      "tipo": "media",
      "circulo": "G",
      "norma": "Reglamento General de Vehículos",
      "articulo": "49",
      "apartado": "4",
      "opc": "5B",
      "puntos": "0",
      "importe": "200 €",
      "importe_reducido": "100 €",
      "descripcion": "Circular con el vehículo cuyas placas de matrícula tienen colocadas, en su parte anterior o posterior, **otras placas, marcas o distintivos que puedan dificultar la legibilidad** o inducir a confusión.",
      "tags": [
        "placas",
        "matricula ilegible",
        "obstaculos"
      ],
      "nota": "",
      "responsables": [
        "Titular"
      ]
    },
    {
      "tipo": "leve",
      "circulo": "L",
      "norma": "Reglamento General de Vehículos",
      "articulo": "50",
      "apartado": "2",
      "opc": "5A",
      "puntos": "0",
      "importe": "80 €",
      "importe_reducido": "40 €",
      "descripcion": "Circular con el vehículo extranjero reseñado sin llevar en su parte posterior el **signo distintivo de la nacionalidad** de su matrícula (V-8).",
      "tags": [
        "placas",
        "circulacion internacional",
        "distintivo nacionalidad"
      ],
      "nota": "No es obligatoria para vehículos con matrícula de la UE",
      "responsables": [
        "Conductor"
      ]
    },
    {
      "tipo": "media",
      "circulo": "G",
      "norma": "Reglamento General de Vehículos",
      "articulo": "50",
      "apartado": "2",
      "opc": "5B",
      "puntos": "0",
      "importe": "200 €",
      "importe_reducido": "100 €",
      "descripcion": "Circular con el vehículo a motor extranjero reseñado, llevando placas de matrícula con un **número distinto al atribuido** por la autoridad competente del país de matriculación.",
      "tags": [
        "placas",
        "circulacion internacional",
        "matricula falsa"
      ],
      "nota": "",
      "responsables": [
        "Conductor"
      ]
    }
  ]
}